{
  "cookies": [
    {
      "name": "session-username",
      "value": "standard_user",
      "domain": "www.saucedemo.com",
      "path": "/",
      "expires": 1777479869,
      "httpOnly": false,
      "secure": false,
      "sameSite": "Lax"
    }
  ],
  "origins": [
    {
      "origin": "https://www.saucedemo.com",
      "localStorage": [
        {
          "name": "backtrace-guid",
          "value": "5778beb2-7e18-4b58-bffd-2df03c722caf"
        },
        {
          "name": "backtrace-last-active",
          "value": "1777479269054"
        }
      ]
    }
  ]
}