{
  "cookies": [
    {
      "name": "session-username",
      "value": "standard_user",
      "domain": "www.saucedemo.com",
      "path": "/",
      "expires": 1771430572,
      "httpOnly": false,
      "secure": false,
      "sameSite": "Lax"
    }
  ],
  "origins": [
    {
      "origin": "https://www.saucedemo.com",
      "localStorage": [
        {
          "name": "backtrace-guid",
          "value": "8f1b0d9b-caf7-4026-95ee-df2d3c23df2e"
        },
        {
          "name": "backtrace-last-active",
          "value": "1771429972212"
        }
      ]
    }
  ]
}